manim_rhythm_graph/__init__.py
manim_rhythm_graph/pie_mobject/__init__.py
manim_rhythm_graph/pie_mobject/get_transform_pairs.py
manim_rhythm_graph/pie_mobject/pie.py
manim_rhythm_graph/pie_mobject/pie_sector.py
manim_rhythm_graph/pie_mobject/radii.py
manim_rhythm_graph/pulse_mobject/__init__.py
manim_rhythm_graph/pulse_mobject/pulse.py
manim_rhythm_graph/rhythm_element.py
manim_rhythm_graph/stick_mobject/__init__.py
manim_rhythm_graph/stick_mobject/stick.py
manim_rhythm_graph-0.1.0.dist-info/entry_points.txt
manim_rhythm_graph-0.1.0.dist-info/METADATA
manim_rhythm_graph-0.1.0.dist-info/WHEEL
manim_rhythm_graph-0.1.0.dist-info/RECORD
